super_collator/__init__.py
super_collator/_version.py
super_collator/aligner.py
super_collator/ngrams.py
super_collator/super_collator.py
super_collator-0.0.5.dist-info/METADATA
super_collator-0.0.5.dist-info/WHEEL
super_collator-0.0.5.dist-info/licenses/LICENSE
super_collator-0.0.5.dist-info/RECORD
