Metadata-Version: 2.1
Name: super-collator
Version: 0.0.5
Summary: Collate textual sources with relaxed spelling.
Project-URL: Homepage, https://github.com/cceh/super-collator
Project-URL: Bug Tracker, https://github.com/cceh/super-collator/issues
Author-email: Marcello Perathoner <marcello@perathoner.de>
License-File: LICENSE
Keywords: collation,collator,needleman-wunsch,needleman-wunsch-gotoh,python
Classifier: Intended Audience :: Developers
Classifier: Intended Audience :: Information Technology
Classifier: Intended Audience :: Science/Research
Classifier: License :: OSI Approved :: GNU General Public License v3 (GPLv3)
Classifier: Operating System :: OS Independent
Classifier: Programming Language :: Python :: 3.9
Classifier: Programming Language :: Python :: 3.10
Classifier: Programming Language :: Python :: 3.11
Classifier: Programming Language :: Python :: 3.12
Classifier: Topic :: Scientific/Engineering :: Bio-Informatics
Classifier: Topic :: Text Processing :: Linguistic
Requires-Python: >=3.9
